adhesive/__init__.py
adhesive/__main__.py
adhesive/kubeapi.py
adhesive/mainapp.py
adhesive/py.typed
adhesive/secrets.py
adhesive/time_patch.py
adhesive/version.py
adhesive/config/AdhesiveConfig.py
adhesive/config/AdhesiveConfigResolver.py
adhesive/config/LocalAdhesiveConfig.py
adhesive/config/LocalConfigReader.py
adhesive/config/NoopAdhesiveConfig.py
adhesive/config/__init__.py
adhesive/consoleui/ConsoleUserTaskProvider.py
adhesive/consoleui/__init__.py
adhesive/consoleui/color_print.py
adhesive/debug/__init__.py
adhesive/execution/ExecutionBaseTask.py
adhesive/execution/ExecutionData.py
adhesive/execution/ExecutionLane.py
adhesive/execution/ExecutionLaneId.py
adhesive/execution/ExecutionLoop.py
adhesive/execution/ExecutionMessageCallbackEvent.py
adhesive/execution/ExecutionMessageEvent.py
adhesive/execution/ExecutionTask.py
adhesive/execution/ExecutionToken.py
adhesive/execution/ExecutionUserTask.py
adhesive/execution/__init__.py
adhesive/execution/call_script_task.py
adhesive/execution/deduplication.py
adhesive/execution/execution_message_callback_event.py
adhesive/execution/execution_message_event.py
adhesive/execution/execution_task.py
adhesive/execution/execution_user_task.py
adhesive/execution/token_utils.py
adhesive/graph/BoundaryEvent.py
adhesive/graph/ComplexGateway.py
adhesive/graph/Edge.py
adhesive/graph/EndEvent.py
adhesive/graph/ErrorBoundaryEvent.py
adhesive/graph/Event.py
adhesive/graph/ExclusiveGateway.py
adhesive/graph/ExecutableNode.py
adhesive/graph/Gateway.py
adhesive/graph/Item.py
adhesive/graph/Lane.py
adhesive/graph/Loop.py
adhesive/graph/MessageEvent.py
adhesive/graph/NamedItem.py
adhesive/graph/NonWaitingGateway.py
adhesive/graph/ParallelGateway.py
adhesive/graph/Process.py
adhesive/graph/ProcessNode.py
adhesive/graph/ProcessTask.py
adhesive/graph/ScriptTask.py
adhesive/graph/StartEvent.py
adhesive/graph/SubProcess.py
adhesive/graph/Task.py
adhesive/graph/UserTask.py
adhesive/graph/WaitingGateway.py
adhesive/graph/__init__.py
adhesive-2021.4.3.dist-info/LICENSE
adhesive-2021.4.3.dist-info/METADATA
adhesive-2021.4.3.dist-info/WHEEL
adhesive-2021.4.3.dist-info/entry_points.txt
adhesive-2021.4.3.dist-info/top_level.txt
adhesive-2021.4.3.dist-info/RECORD
