Metadata-Version: 2.1
Name: adhesive
Version: 2021.4.3
Summary: adhesive
Home-page: UNKNOWN
Author: Bogdan Mustiata
Author-email: bogdan.mustiata@gmail.com
License: BSD
Platform: UNKNOWN
Requires-Dist: addict
Requires-Dist: networkx (==2.3)
Requires-Dist: npyscreen (==4.10.5)
Requires-Dist: colorama (>=0.4.3)
Requires-Dist: termcolor-util (<2.0,>=1.2.0)
Requires-Dist: PyYAML (==5.1.2)
Requires-Dist: click (<8.0,>=7.0)
Requires-Dist: schedule (==0.6.0)
Requires-Dist: python-dateutil (==2.8.1)
Requires-Dist: yamldict (<2.0,>=1.2.0)
Requires-Dist: Pebble (==4.6.1)
Requires-Dist: cached-task (==2021.4.2)
Provides-Extra: ssh
Requires-Dist: paramiko (==2.6.0) ; extra == 'ssh'
